{
    "TaskType":  "OSBuild",
    "TaskVersion":  "20.12.16.1",
    "TaskGuid":  "b85d8663-13d8-4bf2-9b6e-01017ac87204",
    "TaskName":  "Windows 10 Pro x64 20H2",
    "CustomName":  "Windows 10 Pro x64 20H2",
    "OSMFamily":  "Client Professional x64 19042 en-GB",
    "OSMGuid":  "be4d8d00-731b-46a0-b375-291c1c2097eb",
    "Name":  "Windows 10 Pro x64 2009 19042.746 en-GB",
    "ImageName":  "Windows 10 Pro",
    "Arch":  "x64",
    "ReleaseId":  "2009",
    "UBR":  "19042.746",
    "Languages":  [
                      "en-GB"
                  ],
    "EditionId":  "Professional",
    "InstallationType":  "Client",
    "MajorVersion":  "10",
    "Build":  "19042",
    "CreatedTime":  "\/Date(1605754922477)\/",
    "ModifiedTime":  "\/Date(1610977300917)\/",
    "ContentPacks":  null,
    "EnableNetFX3":  "False",
    "WinPEAutoExtraFiles":  "False",
    "RemoveAppxProvisionedPackage":  null,
    "RemoveWindowsCapability":  null,
    "RemoveWindowsPackage":  null,
    "DisableWindowsOptionalFeature":  null,
    "EnableWindowsOptionalFeature":  null,
    "Drivers":  null,
    "ExtraFiles":  null,
    "Scripts":  null,
    "StartLayoutXML":  "",
    "UnattendXML":  "",
    "AddWindowsPackage":  null,
    "AddFeatureOnDemand":  null,
    "WinPEADKPE":  null,
    "WinPEADKRE":  null,
    "WinPEADKSE":  null,
    "WinPEDaRT":  "",
    "WinPEDrivers":  null,
    "WinPEExtraFilesPE":  null,
    "WinPEExtraFilesRE":  null,
    "WinPEExtraFilesSE":  null,
    "WinPEScriptsPE":  null,
    "WinPEScriptsRE":  null,
    "WinPEScriptsSE":  null,
    "LangSetAllIntl":  "",
    "LangSetInputLocale":  "",
    "LangSetSKUIntlDefaults":  "",
    "LangSetSetupUILang":  "",
    "LangSetSysLocale":  "",
    "LangSetUILang":  "",
    "LangSetUILangFallback":  "",
    "LangSetUserLocale":  "",
    "LanguagePack":  null,
    "LanguageInterfacePack":  null,
    "LocalExperiencePacks":  null,
    "LanguageFeature":  null,
    "LanguageCopySources":  null
}
